cmsdism-0.6.1.dist-info/licenses/LICENSE
dismcli/__init__.py
dismcli/__main__.py
dismcli/_version.py
dismcli/config.py
dismcli/cli/__init__.py
dismcli/cli/main.py
dismcli/cli/commands/__init__.py
dismcli/cli/commands/build.py
dismcli/cli/commands/package.py
dismcli/cli/commands/start_api.py
dismcli/lib/__init__.py
dismcli/lib/utils.py
dismcli/lib/builder/__init__.py
dismcli/lib/builder/builder.py
dismcli/lib/builder/input_validator.py
dismcli/lib/package/__init__.py
dismcli/lib/package/minio_uploader.py
dismcli/lib/package/packager.py
dismcli/lib/start_api/__init__.py
dismcli/lib/start_api/start_api.py
dismcli/lib/start_api/runtimes/__init__.py
dismcli/lib/start_api/runtimes/docker_runtime.py
dismcli/lib/start_api/runtimes/podman_runtime.py
dismcli/lib/start_api/runtimes/runtime.py
cmsdism-0.6.1.dist-info/METADATA
cmsdism-0.6.1.dist-info/WHEEL
cmsdism-0.6.1.dist-info/entry_points.txt
cmsdism-0.6.1.dist-info/top_level.txt
cmsdism-0.6.1.dist-info/RECORD
