Metadata-Version: 2.4
Name: cmsdism
Version: 0.6.1
Summary: Command line interface to manage InferenceServices in KServe managed by DIALS.
Author-email: Gabriel Moreira <gabriel.moreira@cern.ch>
Classifier: Programming Language :: Python :: 3.9
Classifier: Programming Language :: Python :: 3.10
Classifier: Programming Language :: Python :: 3.11
Classifier: Programming Language :: Python :: 3.12
Classifier: Development Status :: 4 - Beta
Classifier: Environment :: Console
Requires-Python: >=3.9
License-File: LICENSE
Requires-Dist: click<9.0,>=8.1.8
Requires-Dist: cmsdials<3.0,>=2.0.0rc3
Requires-Dist: dism-core<2.0,>=1.5.1
Requires-Dist: numpy<3.0,>=1.23.5
Requires-Dist: minio<8.0,>=7.2.15
Provides-Extra: docker
Requires-Dist: docker<8.0,>=7.1.0; extra == "docker"
Provides-Extra: podman
Requires-Dist: podman<6.0,>=5.5.0; extra == "podman"
Dynamic: license-file
